Workbook

Sheet Inputs
A1: FAiLLON DEVELOPMENT PRO FORMA
A2: Yellow = editable inputs | Green = calculated
A4: Parameter | B4: Value | C4: Unit | D4: Notes
A5: PROJECT BASICS
A6: Deal Name | B6: Charlotte Multifamily 200 Units
A7: Market | B7: charlotte | D7: Boston/Charlotte/Nashville
A8: Program Type | B8: multifamily
A10: PARCEL & DENSITY
A11: Parcel Size (SF) | B11: 43560 | C11: SF | D11: 1 acre = 43,560 SF
A12: Parcel Size (Acres) | B12: 1 | C12: acres | D12: =SF / 43,560
A13: Floor Area Ratio (FAR) | B13: 3 | C13: x | D13: City zoning - Boston 4-8, Charlotte 2-4
A14: Building Efficiency | B14: 85 | C14: % | D14: Rentable / GFA
A15: Number of Floors | B15: 5 | C15: floors | D15: Based on zoning/FAR
A17: UNIT MIX
A18: Total Units | B18: 200 | C18: units
A19: Avg Unit Size | B19: 950 | C19: SF
A20: Total GFA | B20: 180000 | C20: SF
A21: Hotel Keys | B21: 0 | C21: keys | D21: If hotel
A23: REVENUE
A24: Monthly Rent | B24: 1.85 | C24: $/SF/mo
A25: Stabilized Occupancy | B25: 93 | C25: %
A26: Other Income | B26: 5 | C26: % of rent
A27: Annual Rent Growth | B27: 3 | C27: %
A28: Operating Expense Ratio | B28: 35 | C28: %
A30: COSTS
A31: Land Cost (Total) | B31: 8000000 | C31: $ | D31: Or use per acre
A32: Land Cost per Acre | B32: 500000 | C32: $/acre
A33: Hard Cost | B33: 275 | C33: $/SF | D33: Construction
A34: Soft Cost % | B34: 22 | C34: % | D34: Of hard
A35: Contingency % | B35: 7 | C35: %
A36: Developer Fee % | B36: 4 | C36: %
A38: FINANCING
A39: Loan to Cost | B39: 65 | C39: %
A40: Interest Rate | B40: 7.5 | C40: %
A41: LP Equity % | B41: 90 | C41: %
A43: EXIT
A44: Exit Cap Rate | B44: 5.25 | C44: %
A45: Hold Period | B45: 5 | C45: years
A46: Sale Costs | B46: 2 | C46: %

Sheet Parcel Analysis
A1: PARCEL TO GFA ANALYSIS
A3: Metric | B3: Value | C3: Formula/Notes
A4: PARCEL INPUTS
A5: Parcel SF | B5: =Inputs!B11 | C5: From inputs
A6: Parcel Acres | B6: =Inputs!B11/43560 | C6: SF / 43,560
A8: ZONING & DENSITY
A9: FAR (Floor Area Ratio) | B9: =Inputs!B13 | C9: City zoning allowance
A10: Maximum Buildable GFA | B10: =B5*B9 | C10: Parcel SF × FAR
A12: BUILDING CONFIGURATION
A13: Number of Floors | B13: =Inputs!B15 | C13: Based on zoning/height limits
A14: Typical Floorplate | B14: =B10/B13 | C14: GFA / Floors
A15: Building Efficiency | B15: =Inputs!B14/100 | C15: Rentable / Gross
A16: Total Rentable SF | B16: =B10*B15 | C16: GFA × Efficiency
A18: UNIT ANALYSIS
A19: Avg Unit Size (Input) | B19: =Inputs!B19 | C19: From inputs
A20: Effective Unit Count | B20: =ROUND(B16/B19,0) | C20: Rentable SF / Avg Unit SF
A21: Units per Floor | B21: =ROUND(B20/B13,0) | C21: Total Units / Floors
A23: DENSITY METRICS
A24: Units per Acre | B24: =B20/B6 | C24: Units / Acres
A25: FAR Used | B25: =Inputs!B20/B5 | C25: Actual GFA / Parcel
A26: GFA per Unit | B26: =Inputs!B20/Inputs!B18 | C26: Gross SF / Units
A29: CITY FAR GUIDELINES:
A30: • Boston: FAR 4-8 (high density, transit-oriented)
A31: • Charlotte: FAR 2-4 (mid-rise suburban/urban)
A32: • Nashville: FAR 2-4 (similar to Charlotte)

Sheet Calculations
A1: FINANCIAL CALCULATIONS
A3: Item | B3: Value | C3: Formula
A4: REVENUE
A5: Rentable SF | B5: =Inputs!B18*Inputs!B19 | C5: Units × Avg SF
A6: Gross Potential Rent | B6: =B5*Inputs!B24*12 | C6: Rentable × Rent × 12
A7: Other Income | B7: =B6*Inputs!B26/100 | C7: GPR × Other %
A8: Gross Potential Income | B8: =B6+B7 | C8: Rent + Other
A9: Vacancy Loss | B9: =B8*(1-Inputs!B25/100) | C9: GPI × (1-Occ)
A10: Effective Gross Income | B10: =B8-B9 | C10: GPI - Vacancy
A11: Operating Expenses | B11: =B10*Inputs!B28/100 | C11: EGI × OpEx%
A12: Net Operating Income | B12: =B10-B11 | C12: EGI - OpEx
A14: COSTS
A15: Land Cost | B15: =IF(Inputs!B31>0,Inputs!B31,Inputs!B32*Inputs!B12) | C15: Total or Per Acre × Acres
A16: Hard Costs | B16: =Inputs!B20*Inputs!B33 | C16: GFA × $/SF
A17: Soft Costs | B17: =B16*Inputs!B34/100 | C17: Hard × Soft%
A18: Contingency | B18: =(B16+B17)*Inputs!B35/100 | C18: (H+S) × Cont%
A19: Subtotal | B19: =B15+B16+B17+B18 | C19: Land+Hard+Soft+Cont
A20: Developer Fee | B20: =B19*Inputs!B36/100 | C20: Sub × Fee%
A21: Total Development Cost | B21: =B19+B20 | C21: Subtotal + Fee
A23: FINANCING
A24: Loan Amount | B24: =B21*Inputs!B39/100 | C24: TDC × LTC%
A25: Total Equity | B25: =B21-B24 | C25: TDC - Loan
A26: LP Equity | B26: =B25*Inputs!B41/100 | C26: Equity × LP%
A27: GP Equity | B27: =B25-B26 | C27: Equity - LP
A29: RETURNS
A30: Exit Value (Gross) | B30: =B12/(Inputs!B44/100) | C30: NOI / Cap Rate
A31: Sale Costs | B31: =B30*Inputs!B46/100 | C31: Gross × Sale%
A32: Exit Value (Net) | B32: =B30-B31 | C32: Gross - Sale
A33: Total Profit | B33: =B32-B21 | C33: Net Exit - TDC
A34: Profit on Cost | B34: =B33/B21 | C34: Profit / TDC
A35: Cost per Unit | B35: =B21/Inputs!B18 | C35: TDC / Units
A36: NOI Yield on Cost | B36: =B12/B21 | C36: NOI / TDC

Sheet Unit Scenarios
A1: UNIT MIX SCENARIO ANALYSIS
A2: Same GFA, different unit counts = different avg sizes
A4: Metric | B4: N-20 | C4: N-10 | D4: Base | E4: N+10 | F4: N+20
A5: Unit Count | B5: =Inputs!B18+-20 | C5: =Inputs!B18+-10 | D5: =Inputs!B18+0 | E5: =Inputs!B18+10 | F5: =Inputs!B18+20
A6: Avg Unit SF | B6: =Inputs!B20/B5 | C6: =Inputs!B20/C5 | D6: =Inputs!B20/D5 | E6: =Inputs!B20/E5 | F6: =Inputs!B20/F5
A7: Rentable SF | B7: =B5*B6 | C7: =C5*C6 | D7: =D5*D6 | E7: =E5*E6 | F7: =F5*F6
A8: Annual Rent | B8: =B7*Inputs!B24*12 | C8: =C7*Inputs!B24*12 | D8: =D7*Inputs!B24*12 | E8: =E7*Inputs!B24*12 | F8: =F7*Inputs!B24*12
A9: EGI | B9: =B8*(1+Inputs!B26/100)*(Inputs!B25/100) | C9: =C8*(1+Inputs!B26/100)*(Inputs!B25/100) | D9: =D8*(1+Inputs!B26/100)*(Inputs!B25/100) | E9: =E8*(1+Inputs!B26/100)*(Inputs!B25/100) | F9: =F8*(1+Inputs!B26/100)*(Inputs!B25/100)
A10: NOI | B10: =B9*(1-Inputs!B28/100) | C10: =C9*(1-Inputs!B28/100) | D10: =D9*(1-Inputs!B28/100) | E10: =E9*(1-Inputs!B28/100) | F10: =F9*(1-Inputs!B28/100)
A12: COSTS (Fixed GFA)
A13: Total Dev Cost | B13: =(IF(Inputs!B31>0,Inputs!B31,Inputs!B32*Inputs!B12)+Inputs!B20*Inputs!B33*(1+Inputs!B34/100)*(1+Inputs!B35/100))*(1+Inputs!B36/100) | C13: =(IF(Inputs!B31>0,Inputs!B31,Inputs!B32*Inputs!B12)+Inputs!B20*Inputs!B33*(1+Inputs!B34/100)*(1+Inputs!B35/100))*(1+Inputs!B36/100) | D13: =(IF(Inputs!B31>0,Inputs!B31,Inputs!B32*Inputs!B12)+Inputs!B20*Inputs!B33*(1+Inputs!B34/100)*(1+Inputs!B35/100))*(1+Inputs!B36/100) | E13: =(IF(Inputs!B31>0,Inputs!B31,Inputs!B32*Inputs!B12)+Inputs!B20*Inputs!B33*(1+Inputs!B34/100)*(1+Inputs!B35/100))*(1+Inputs!B36/100) | F13: =(IF(Inputs!B31>0,Inputs!B31,Inputs!B32*Inputs!B12)+Inputs!B20*Inputs!B33*(1+Inputs!B34/100)*(1+Inputs!B35/100))*(1+Inputs!B36/100)
A14: Cost per Unit | B14: =B13/B5 | C14: =C13/C5 | D14: =D13/D5 | E14: =E13/E5 | F14: =F13/F5
A16: RETURNS
A17: Exit Value (Net) | B17: =(B10/(Inputs!B44/100))*(1-Inputs!B46/100) | C17: =(C10/(Inputs!B44/100))*(1-Inputs!B46/100) | D17: =(D10/(Inputs!B44/100))*(1-Inputs!B46/100) | E17: =(E10/(Inputs!B44/100))*(1-Inputs!B46/100) | F17: =(F10/(Inputs!B44/100))*(1-Inputs!B46/100)
A18: Profit | B18: =B17-B13 | C18: =C17-C13 | D18: =D17-D13 | E18: =E17-E13 | F18: =F17-F13
A19: Profit on Cost | B19: =B18/B13 | C19: =C18/C13 | D19: =D18/D13 | E19: =E18/E13 | F19: =F18/F13

Sheet Sensitivity
A1: SENSITIVITY ANALYSIS
A3: Exit Cap \ Cost | B3: -10% | C3: Base | D3: +10%
A4: 4.75% | B4: 12.7 | C4: 6.3 | D4: 1.9
A5: 5.25% | B5: 8 | C5: 2 | D5: -2
A6: 5.75% | B6: 3.3 | C6: -2.2 | D6: -5.8

Sheet Summary
A1: Charlotte Multifamily 200 Units
A3: Market | B3: =Inputs!B7
A4: Parcel (Acres) | B4: =Inputs!B12
A5: Total GFA | B5: =Inputs!B20
A6: Unit Count | B6: =Inputs!B18
A7: Exit Cap | B7: =Inputs!B44
